MANIFEST.in
README.md
setup.py
ocx_client/__init__.py
ocx_client/auth.py
ocx_client/client.py
ocx_client/error.py
ocx_client/streaming_client.py
ocx_client.egg-info/PKG-INFO
ocx_client.egg-info/SOURCES.txt
ocx_client.egg-info/dependency_links.txt
ocx_client.egg-info/not-zip-safe
ocx_client.egg-info/requires.txt
ocx_client.egg-info/top_level.txt