Metadata-Version: 1.0
Name: ocx-client
Version: 0.1.0
Summary: a client library for the bitcoin exchange OCX
Home-page: https://github.com/ocxapi/ocx-openapi-ruby-client
Author: nju520
Author-email: UNKNOWN
License: LGPL
Keywords: bitcoin ocx ocx.com
Platform: UNKNOWN
